sacred/__about__.py
sacred/__init__.py
sacred/arg_parser.py
sacred/commandline_options.py
sacred/commands.py
sacred/config_helpers.py
sacred/dependencies.py
sacred/experiment.py
sacred/host_info.py
sacred/ingredient.py
sacred/initialize.py
sacred/metrics_logger.py
sacred/optional.py
sacred/py.typed
sacred/pytee.py
sacred/randomness.py
sacred/run.py
sacred/serializer.py
sacred/settings.py
sacred/stdout_capturing.py
sacred/utils.py
sacred/config/__init__.py
sacred/config/captured_function.py
sacred/config/config_dict.py
sacred/config/config_files.py
sacred/config/config_scope.py
sacred/config/config_summary.py
sacred/config/custom_containers.py
sacred/config/signature.py
sacred/config/utils.py
sacred/data/mime.types
sacred/observers/__init__.py
sacred/observers/base.py
sacred/observers/file_storage.py
sacred/observers/gcs_observer.py
sacred/observers/mongo.py
sacred/observers/queue.py
sacred/observers/s3_observer.py
sacred/observers/slack.py
sacred/observers/sql.py
sacred/observers/sql_bases.py
sacred/observers/telegram_obs.py
sacred/observers/tinydb_hashfs/__init__.py
sacred/observers/tinydb_hashfs/bases.py
sacred/observers/tinydb_hashfs/tinydb_hashfs.py
sacred/stflow/__init__.py
sacred/stflow/internal.py
sacred/stflow/method_interception.py
kk_sacred-0.8.5.dist-info/LICENSE.txt
kk_sacred-0.8.5.dist-info/METADATA
kk_sacred-0.8.5.dist-info/WHEEL
kk_sacred-0.8.5.dist-info/top_level.txt
kk_sacred-0.8.5.dist-info/RECORD
